{
    "$id": "https://commongateway.nl/schema/xxllnctoktb.notification.schema.json",
    "$schema": "https://docs.commongateway.nl/schemas/Entity.schema.json",
    "version": "0.0.1",
    "title": "Notification",
    "description": "A notification object from xxllnc",
    "type": "object",
    "properties": {
        "case_number": {
            "type": "integer"
        },
        "entity_id": {
            "type": "string"
        },
        "case_uuid": {
            "type": "string"
        },
        "changes": {
            "type": "array",
            "format": "json"
        },
        "entity_type": {
            "type": "string"
        },
        "event_name": {
            "type": "string"
        },
        "description": {
            "type": "string"
        }
    }
  }