{
    "installationService": "CommonGateway\\XxllncToKTBBundle\\Service\\InstallationService",
    "applications": [],
    "users": [],
    "cards": [],
    "actions": [],
    "collections": [],
    "endpoints": {
        "schema": [
            {
                "reference": "https://commongateway.nl/schema/xxllnctoktb.notification.schema.json",
                "description": "An endpoint for notifications from xxllnc zaaksysteem",
                "path": "/xxllnc/notifications",
                "version": "0.0.1",
                "methods": [
                    "POST",
                    "GET"
                ],
                "throws": [
                    "xxllnctoktb.notification.task"
                ]
            }
        ]
    }
}